odoo8_addon_oca_custom-8.0.0.0.0-py2.7-nspkg.pth
odoo8_addon_oca_custom-8.0.0.0.0.dist-info/top_level.txt
odoo8_addon_oca_custom-8.0.0.0.0.dist-info/WHEEL
odoo8_addon_oca_custom-8.0.0.0.0.dist-info/RECORD
odoo8_addon_oca_custom-8.0.0.0.0.dist-info/metadata.json
odoo8_addon_oca_custom-8.0.0.0.0.dist-info/DESCRIPTION.rst
odoo8_addon_oca_custom-8.0.0.0.0.dist-info/METADATA
odoo8_addon_oca_custom-8.0.0.0.0.dist-info/namespace_packages.txt
odoo_addons/oca_custom/__openerp__.py
odoo_addons/oca_custom/__init__.py
odoo_addons/oca_custom/README.rst
odoo_addons/oca_custom/models/res_partner.py
odoo_addons/oca_custom/models/__init__.py
odoo_addons/oca_custom/views/view_res_partner.xml
odoo_addons/oca_custom/static/description/icon.png
